github_file_loader/__init__.py
github_file_loader/__main__.py
github_file_loader/client.py
github_file_loader/file_loader.py
github_file_loader/parser.py
github_file_loader/core/__init__.py
github_file_loader/core/config.py
github_file_loader/core/exceptions.py
github_file_loader/core/types.py
github_file_loader-0.2.0.dist-info/METADATA
github_file_loader-0.2.0.dist-info/WHEEL
github_file_loader-0.2.0.dist-info/entry_points.txt
github_file_loader-0.2.0.dist-info/RECORD
