Metadata-Version: 2.4
Name: github-file-loader
Version: 0.2.0
Summary: A Python package for loading files from GitHub repositories with async support and file filtering
Project-URL: Homepage, https://github.com/md-abid-hussain/github-file-loader
Project-URL: Documentation, https://github.com/md-abid-hussain/github-file-loader#readme
Project-URL: Repository, https://github.com/md-abid-hussain/github-file-loader.git
Project-URL: Bug Reports, https://github.com/md-abid-hussain/github-file-loader/issues
Project-URL: Changelog, https://github.com/md-abid-hussain/github-file-loader/blob/main/CHANGELOG.md
Author-email: Md Abid Hussain <abid0hussain1733@gmail.com>
License: MIT
Keywords: api,async,files,github,loader
Classifier: Development Status :: 4 - Beta
Classifier: Intended Audience :: Developers
Classifier: License :: OSI Approved :: MIT License
Classifier: Programming Language :: Python :: 3
Classifier: Programming Language :: Python :: 3.8
Classifier: Programming Language :: Python :: 3.9
Classifier: Programming Language :: Python :: 3.10
Classifier: Programming Language :: Python :: 3.11
Classifier: Programming Language :: Python :: 3.12
Classifier: Programming Language :: Python :: 3.13
Classifier: Topic :: Internet :: WWW/HTTP :: Dynamic Content
Classifier: Topic :: Software Development :: Libraries :: Python Modules
Requires-Python: >=3.8
Requires-Dist: aiohttp>=3.8.0
Requires-Dist: requests>=2.25.0
Provides-Extra: dev
Requires-Dist: black>=22.0.0; extra == 'dev'
Requires-Dist: build>=0.8.0; extra == 'dev'
Requires-Dist: isort>=5.0.0; extra == 'dev'
Requires-Dist: mypy>=0.950; extra == 'dev'
Requires-Dist: pytest-asyncio>=0.20.0; extra == 'dev'
Requires-Dist: pytest>=6.0; extra == 'dev'
Requires-Dist: twine>=4.0.0; extra == 'dev'
